Metadata-Version: 1.1
Name: omdb-cli
Version: 0.1.0
Summary: A command line tool for The Open Movie Database API
Home-page: https://github.com/juanpabloaj/omdb-cli
Author: JuanPablo AJ
Author-email: jpabloaj@gmail.com
License: MIT
Platform: UNKNOWN
Classifier: Programming Language :: Python
Classifier: Programming Language :: Python :: 3.5
